dyff/schema/__init__.py
dyff/schema/_version.py
dyff/schema/adapters.py
dyff/schema/annotations.py
dyff/schema/base.py
dyff/schema/commands.py
dyff/schema/copydoc.py
dyff/schema/errors.py
dyff/schema/ids.py
dyff/schema/platform.py
dyff/schema/py.typed
dyff/schema/quantity.py
dyff/schema/requests.py
dyff/schema/responses.py
dyff/schema/test.py
dyff/schema/version.py
dyff/schema/dataset/__init__.py
dyff/schema/dataset/arrow.py
dyff/schema/dataset/binary.py
dyff/schema/dataset/classification.py
dyff/schema/dataset/embedding.py
dyff/schema/dataset/text.py
dyff/schema/dataset/vision.py
dyff/schema/io/__init__.py
dyff/schema/io/vllm.py
dyff/schema/v0/__init__.py
dyff/schema/v0/r1/__init__.py
dyff/schema/v0/r1/adapters.py
dyff/schema/v0/r1/base.py
dyff/schema/v0/r1/commands.py
dyff/schema/v0/r1/oci.py
dyff/schema/v0/r1/platform.py
dyff/schema/v0/r1/requests.py
dyff/schema/v0/r1/responses.py
dyff/schema/v0/r1/test.py
dyff/schema/v0/r1/version.py
dyff/schema/v0/r1/dataset/__init__.py
dyff/schema/v0/r1/dataset/arrow.py
dyff/schema/v0/r1/dataset/binary.py
dyff/schema/v0/r1/dataset/classification.py
dyff/schema/v0/r1/dataset/embedding.py
dyff/schema/v0/r1/dataset/text.py
dyff/schema/v0/r1/dataset/vision.py
dyff/schema/v0/r1/io/__init__.py
dyff/schema/v0/r1/io/vllm.py
dyff_schema-0.44.1.dist-info/licenses/LICENSE
dyff_schema-0.44.1.dist-info/licenses/NOTICE
dyff_schema-0.44.1.dist-info/METADATA
dyff_schema-0.44.1.dist-info/WHEEL
dyff_schema-0.44.1.dist-info/top_level.txt
dyff_schema-0.44.1.dist-info/RECORD
