Metadata-Version: 2.4
Name: dyff-schema
Version: 0.44.1
Summary: Data models for the Dyff AI auditing platform.
Author-email: Digital Safety Research Institute <contact@dsri.org>
License: Apache-2.0
Project-URL: Home, https://gitlab.com/dyff/packages/dyff-schema
Project-URL: Issues, https://gitlab.com/dyff/packages/dyff-schema/-/issues
Keywords: ai,audit,safety,evaluation
Classifier: Development Status :: 3 - Alpha
Classifier: Intended Audience :: Science/Research
Classifier: License :: OSI Approved :: Apache Software License
Classifier: Operating System :: OS Independent
Classifier: Programming Language :: Python :: 3
Classifier: Programming Language :: Python :: 3.10
Classifier: Programming Language :: Python :: 3.11
Classifier: Programming Language :: Python :: 3.12
Classifier: Topic :: Scientific/Engineering :: Artificial Intelligence
Requires-Python: >=3.10
License-File: LICENSE
License-File: NOTICE
Requires-Dist: canonicaljson==2.0.0
Requires-Dist: email-validator
Requires-Dist: google-i18n-address
Requires-Dist: hypothesis
Requires-Dist: hypothesis-jsonschema
Requires-Dist: jsonpath-ng
Requires-Dist: numpy<2
Requires-Dist: pyarrow
Requires-Dist: pydantic<3.0.0,>=2.0.0
Provides-Extra: dev
Requires-Dist: pytest; extra == "dev"
Dynamic: license-file
